{"cameraMode":{"drawMode":0,"name":"Shaded","section":"Shading Mode"},"sceneLighting":true,"audioPlay":false,"sceneViewState":{"showFog":true,"showMaterialUpdate":false,"showSkybox":true,"showFlares":true,"showImageEffects":true,"showParticleSystems":true,"showVisualEffectGraphs":true,"m_FxEnabled":true},"in2DMode":false,"pivot":{"x":373.6658630371094,"y":349.87451171875,"z":18.23387336730957},"rotation":{"x":-0.26809459924697878,"y":-0.24350424110889436,"z":0.07024113833904267,"w":-0.9295017719268799},"size":0.39589399099349978,"orthographic":false}